Schedy-0.1.0b6.dist-info/DESCRIPTION.rst
Schedy-0.1.0b6.dist-info/METADATA
Schedy-0.1.0b6.dist-info/RECORD
Schedy-0.1.0b6.dist-info/WHEEL
Schedy-0.1.0b6.dist-info/entry_points.txt
Schedy-0.1.0b6.dist-info/metadata.json
Schedy-0.1.0b6.dist-info/top_level.txt
schedy/__init__.py
schedy/cmd.py
schedy/compat.py
schedy/core.py
schedy/encoding.py
schedy/errors.py
schedy/experiments.py
schedy/jobs.py
schedy/jwt.py
schedy/pagination.py
schedy/pbt.py
schedy/random.py
schedy/test_core.py
