Metadata-Version: 2.0
Name: Schedy
Version: 0.1.0b6
Summary: Python client for Schedy
Home-page: https://schedy.io/
Author: Incalia
Author-email: nathan@incalia.fr
License: MIT
Project-URL: Source, https://github.com/incalia/schedy-client/
Project-URL: Documentation, https://schedy.readthedocs.io/en/latest/
Project-URL: Homepage, https://schedy.io/
Platform: UNKNOWN
Classifier: Intended Audience :: Developers
Classifier: Intended Audience :: Education
Classifier: Intended Audience :: Science/Research
Classifier: Programming Language :: Python :: 2
Classifier: Programming Language :: Python :: 2.7
Classifier: Programming Language :: Python :: 3
Classifier: Programming Language :: Python :: 3.4
Classifier: Programming Language :: Python :: 3.5
Classifier: Programming Language :: Python :: 3.6
Classifier: Development Status :: 4 - Beta
Classifier: Topic :: Scientific/Engineering :: Artificial Intelligence
Classifier: Topic :: Software Development :: Libraries :: Python Modules
Requires-Dist: requests (>=2.18.4)
Requires-Dist: six (>=1.11.0)
Requires-Dist: tabulate (>=0.8.2)
